os_api_ref/__init__.py
os_api_ref/http_codes.py
os_api_ref/assets/api-site.css
os_api_ref/assets/api-site.js
os_api_ref/assets/glyphicons-halflings-regular.ttf
os_api_ref/assets/glyphicons-halflings-regular.woff
os_api_ref/tests/__init__.py
os_api_ref/tests/base.py
os_api_ref/tests/test_basic_example.py
os_api_ref/tests/test_microversions.py
os_api_ref/tests/test_os_api_ref.py
os_api_ref/tests/test_warnings.py
os_api_ref/tests/examples/basic/conf.py
os_api_ref/tests/examples/basic/index.rst
os_api_ref/tests/examples/basic/parameters.yaml
os_api_ref/tests/examples/basic/status.yaml
os_api_ref/tests/examples/microversions/conf.py
os_api_ref/tests/examples/microversions/index.rst
os_api_ref/tests/examples/microversions/parameters.yaml
os_api_ref/tests/examples/warnings/conf.py
os_api_ref/tests/examples/warnings/empty_parameters_file.yaml
os_api_ref/tests/examples/warnings/index.rst
os_api_ref/tests/examples/warnings/parameters.yaml
os_api_ref-3.1.0.dist-info/AUTHORS
os_api_ref-3.1.0.dist-info/LICENSE
os_api_ref-3.1.0.dist-info/METADATA
os_api_ref-3.1.0.dist-info/WHEEL
os_api_ref-3.1.0.dist-info/pbr.json
os_api_ref-3.1.0.dist-info/top_level.txt
os_api_ref-3.1.0.dist-info/RECORD
